calcalc/CalCalc.py
calcalc/__init__.py
calcalc/tests/__init__.py
calcalc/tests/test_calculate.py
CalcalcZB-0.0.2.dist-info/LICENSE.txt
CalcalcZB-0.0.2.dist-info/METADATA
CalcalcZB-0.0.2.dist-info/WHEEL
CalcalcZB-0.0.2.dist-info/top_level.txt
CalcalcZB-0.0.2.dist-info/RECORD
