Metadata-Version: 2.1
Name: CalcalcZB
Version: 0.0.2
Summary: AY250 HW3: evaluate numeric string expressions.
Home-page: https://github.com/zbalewski/python-ay250-homework/tree/main/hw_3
Author: Zuzanna Balewski
Author-email: balewski@berkeley.edu
License: MIT
Platform: any
Classifier: Development Status :: 2 - Pre-Alpha
Classifier: Intended Audience :: Education
Classifier: License :: OSI Approved :: MIT License
Classifier: Programming Language :: Python
Classifier: Programming Language :: Python :: 3.5
Classifier: Programming Language :: Python :: 3.6
Classifier: Programming Language :: Python :: 3.7
Classifier: Programming Language :: Python :: 3.8
Classifier: Programming Language :: Python :: 3.9
Classifier: Topic :: Scientific/Engineering
Requires-Python: >=3
License-File: LICENSE.txt
Requires-Dist: numexpr
Requires-Dist: urllib3
Requires-Dist: requests
